<?xml version="1.0" encoding="UTF-8" standalone="yes"?>
<tournament>
    <tourid>football-4987</tourid>
    <touridshort>4987</touridshort>
    <tourname>МИР Российская Премьер-лига</tourname>
    <matches>
        <match>
            <type>match</type>
            <id>football-1040491</id>
            <played>1</played>
            <link>/football/_russiapl/tournament/4987/match/1040491/</link>
            <group/>
            <tourstr>27</tourstr>
            <date>2023-05-14</date>
            <time>19:00</time>
            <team1>Сочи</team1>
            <team2>Ростов</team2>
            <score1>1</score1>
            <score2>0</score2>
            <score1ext/>
            <score2ext/>
            <live/>
            <liveperiod/>
        </match>
        <match>
            <type>match</type>
            <id>football-1040493</id>
            <played>1</played>
            <link>/football/_russiapl/tournament/4987/match/1040493/</link>
            <group/>
            <tourstr>27</tourstr>
            <date>2023-05-14</date>
            <time>19:00</time>
            <team1>Факел</team1>
            <team2>Пари Нижний Новгород</team2>
            <score1>1</score1>
            <score2>0</score2>
            <score1ext/>
            <score2ext/>
            <live/>
            <liveperiod/>
        </match>
        <match>
            <type>match</type>
            <id>football-1040489</id>
            <played>1</played>
            <link>/football/_russiapl/tournament/4987/match/1040489/</link>
            <group/>
            <tourstr>27</tourstr>
            <date>2023-05-14</date>
            <time>16:30</time>
            <team1>Динамо М</team1>
            <team2>Ахмат</team2>
            <score1>0</score1>
            <score2>3</score2>
            <score1ext/>
            <score2ext/>
            <live/>
            <liveperiod/>
        </match>
        <match>
            <type>match</type>
            <id>football-1040485</id>
            <played>1</played>
            <link>/football/_russiapl/tournament/4987/match/1040485/</link>
            <group/>
            <tourstr>27</tourstr>
            <date>2023-05-14</date>
            <time>14:00</time>
            <team1>Крылья Советов</team1>
            <team2>Локомотив М</team2>
            <score1>1</score1>
            <score2>1</score2>
            <score1ext/>
            <score2ext/>
            <live/>
            <liveperiod/>
        </match>
        <match>
            <type>match</type>
            <id>football-1040487</id>
            <played>1</played>
            <link>/football/_russiapl/tournament/4987/match/1040487/</link>
            <group/>
            <tourstr>27</tourstr>
            <date>2023-05-13</date>
            <time>19:00</time>
            <team1>ЦСКА</team1>
            <team2>Торпедо М</team2>
            <score1>3</score1>
            <score2>0</score2>
            <score1ext/>
            <score2ext/>
            <live/>
            <liveperiod/>
        </match>
        <match>
            <type>match</type>
            <id>football-1040483</id>
            <played>1</played>
            <link>/football/_russiapl/tournament/4987/match/1040483/</link>
            <group/>
            <tourstr>27</tourstr>
            <date>2023-05-13</date>
            <time>16:30</time>
            <team1>Зенит</team1>
            <team2>Краснодар</team2>
            <score1>2</score1>
            <score2>2</score2>
            <score1ext/>
            <score2ext/>
            <live/>
            <liveperiod/>
        </match>
        <match>
            <type>match</type>
            <id>football-1040497</id>
            <played>1</played>
            <link>/football/_russiapl/tournament/4987/match/1040497/</link>
            <group/>
            <tourstr>27</tourstr>
            <date>2023-05-13</date>
            <time>14:00</time>
            <team1>Химки</team1>
            <team2>Спартак М</team2>
            <score1>1</score1>
            <score2>1</score2>
            <score1ext/>
            <score2ext/>
            <live/>
            <liveperiod/>
        </match>
        <match>
            <type>match</type>
            <id>football-1040495</id>
            <played>1</played>
            <link>/football/_russiapl/tournament/4987/match/1040495/</link>
            <group/>
            <tourstr>27</tourstr>
            <date>2023-05-13</date>
            <time>12:00</time>
            <team1>Урал</team1>
            <team2>Оренбург</team2>
            <score1>2</score1>
            <score2>1</score2>
            <score1ext/>
            <score2ext/>
            <live/>
            <liveperiod/>
        </match>
        <match>
            <type>match</type>
            <id>football-1040475</id>
            <played>1</played>
            <link>/football/_russiapl/tournament/4987/match/1040475/</link>
            <group/>
            <tourstr>26</tourstr>
            <date>2023-05-08</date>
            <time>17:00</time>
            <team1>Локомотив М</team1>
            <team2>Сочи</team2>
            <score1>3</score1>
            <score2>0</score2>
            <score1ext/>
            <score2ext/>
            <live/>
            <liveperiod/>
        </match>
        <match>
            <type>match</type>
            <id>football-1040471</id>
            <played>1</played>
            <link>/football/_russiapl/tournament/4987/match/1040471/</link>
            <group/>
            <tourstr>26</tourstr>
            <date>2023-05-07</date>
            <time>19:00</time>
            <team1>Краснодар</team1>
            <team2>Крылья Советов</team2>
            <score1>2</score1>
            <score2>1</score2>
            <score1ext/>
            <score2ext/>
            <live/>
            <liveperiod/>
        </match>
    </matches>
</tournament>
